[
    {"title":"Sosialt","imageName":"Hamburg.jpg", "text":"<p>Jeg digger salsa for den muligheten du har til å dra ut i verden og møte nye folk gjennom en felles aktivitet. I løpet av det siste året har jeg reist til kule steder.</p><p>Til venstre er et bilde fra turen vår til Hamburg sist sommer</p> "},
    {"title":"Brussel","imageName":"Brussel_Edyta.jpg", "text":"<p>På Mambomania, i Oslo, var jeg med på en solokonkurranse. Dommeren var utrolig grei og ga meg et gratis pass til festivalen hans i Brussel. Der fikk jeg være med på flere gode kurs og danse natten lang.</p> Spesielt gøy er det å danse med proffe instruktører, slik som Edyta Czagowiec.<br><a href='https://www.facebook.com/STARMAMBOVIDEO75000/videos/190365398702165/' target='_blank'>Her er link til en av dansene vi hadde</a> "},
    {"title":"Wien","imageName":"Wien_Alexandra.jpg", "text":"I forbindelse med showet vårt i Wien fikk vi masse tid til å sosialdanse."}
]